tensorcircuit/__init__.py
tensorcircuit/about.py
tensorcircuit/abstractcircuit.py
tensorcircuit/asciiart.py
tensorcircuit/basecircuit.py
tensorcircuit/channels.py
tensorcircuit/circuit.py
tensorcircuit/cons.py
tensorcircuit/densitymatrix.py
tensorcircuit/experimental.py
tensorcircuit/fgs.py
tensorcircuit/gates.py
tensorcircuit/keras.py
tensorcircuit/mps_base.py
tensorcircuit/mpscircuit.py
tensorcircuit/noisemodel.py
tensorcircuit/quantum.py
tensorcircuit/quditcircuit.py
tensorcircuit/quditgates.py
tensorcircuit/shadows.py
tensorcircuit/simplify.py
tensorcircuit/stabilizercircuit.py
tensorcircuit/timeevol.py
tensorcircuit/torchnn.py
tensorcircuit/translation.py
tensorcircuit/utils.py
tensorcircuit/vis.py
tensorcircuit/applications/__init__.py
tensorcircuit/applications/dqas.py
tensorcircuit/applications/graphdata.py
tensorcircuit/applications/layers.py
tensorcircuit/applications/optimization.py
tensorcircuit/applications/utils.py
tensorcircuit/applications/vags.py
tensorcircuit/applications/van.py
tensorcircuit/applications/vqes.py
tensorcircuit/applications/ai/__init__.py
tensorcircuit/applications/ai/ensemble.py
tensorcircuit/applications/finance/__init__.py
tensorcircuit/applications/finance/portfolio.py
tensorcircuit/applications/physics/__init__.py
tensorcircuit/applications/physics/baseline.py
tensorcircuit/applications/physics/fss.py
tensorcircuit/backends/__init__.py
tensorcircuit/backends/abstract_backend.py
tensorcircuit/backends/backend_factory.py
tensorcircuit/backends/cupy_backend.py
tensorcircuit/backends/jax_backend.py
tensorcircuit/backends/jax_ops.py
tensorcircuit/backends/numpy_backend.py
tensorcircuit/backends/pytorch_backend.py
tensorcircuit/backends/pytorch_ops.py
tensorcircuit/backends/tensorflow_backend.py
tensorcircuit/backends/tf_ops.py
tensorcircuit/cloud/__init__.py
tensorcircuit/cloud/abstraction.py
tensorcircuit/cloud/apis.py
tensorcircuit/cloud/config.py
tensorcircuit/cloud/local.py
tensorcircuit/cloud/quafu_provider.py
tensorcircuit_ng-1.4.0.dist-info/licenses/LICENSE
tensorcircuit_ng-1.4.0.dist-info/METADATA
tensorcircuit_ng-1.4.0.dist-info/WHEEL
tensorcircuit_ng-1.4.0.dist-info/top_level.txt
tensorcircuit_ng-1.4.0.dist-info/RECORD
