Metadata-Version: 2.4
Name: tensorcircuit-ng
Version: 1.4.0
Summary: High performance unified quantum computing framework for the NISQ era
Author-email: TensorCircuit Authors <znfesnpbh@gmail.com>
License-Expression: Apache-2.0
Project-URL: Homepage, https://github.com/tensorcircuit/tensorcircuit-ng
Project-URL: Repository, https://github.com/tensorcircuit/tensorcircuit-ng
Classifier: Programming Language :: Python :: 3
Classifier: Operating System :: OS Independent
Classifier: Intended Audience :: Science/Research
Classifier: Topic :: Scientific/Engineering :: Physics
Requires-Python: >=3.9
License-File: LICENSE
Requires-Dist: numpy
Requires-Dist: scipy
Requires-Dist: tensornetwork-ng
Requires-Dist: networkx
Provides-Extra: tensorflow
Requires-Dist: tensorflow; extra == "tensorflow"
Provides-Extra: jax
Requires-Dist: jax; extra == "jax"
Requires-Dist: jaxlib; extra == "jax"
Provides-Extra: torch
Requires-Dist: torch; extra == "torch"
Provides-Extra: qiskit
Requires-Dist: qiskit; extra == "qiskit"
Requires-Dist: sympy; extra == "qiskit"
Requires-Dist: symengine; extra == "qiskit"
Provides-Extra: cloud
Requires-Dist: qiskit; extra == "cloud"
Requires-Dist: mthree<2.8; extra == "cloud"
Dynamic: license-file
